djwsbridge/__init__.py
djwsbridge/apps.py
djwsbridge/asgi.py
djwsbridge/bridge.py
djwsbridge/consumers.py
djwsbridge/middleware.py
djwsbridge/routing.py
djwsbridge/utils.py
djwsbridge-0.1.3.dist-info/METADATA
djwsbridge-0.1.3.dist-info/WHEEL
djwsbridge-0.1.3.dist-info/top_level.txt
djwsbridge-0.1.3.dist-info/RECORD
